setup.py
hmlstm/__init__.py
hmlstm/hmlstm_cell.py
hmlstm/hmlstm_network.py
hmlstm/multi_hmlstm_cell.py
hmlstm.egg-info/PKG-INFO
hmlstm.egg-info/SOURCES.txt
hmlstm.egg-info/dependency_links.txt
hmlstm.egg-info/top_level.txt