Metadata-Version: 1.0
Name: hmlstm
Version: 0.0.1
Summary: Implementation of hierarchical multiscale hlstm network
Home-page: https://github.com/n-s-f/hierarchical-rnn
Author: UNKNOWN
Author-email: UNKNOWN
License: UNKNOWN
Platform: UNKNOWN
